{
  "config": {
    "steps": 700,
    "lr": 0.02,
    "tau_start": 1.0,
    "tau_end": 0.03,
    "sinkhorn_iters": 30,
    "lambda_ent": 0.0003,
    "train_subsample": 0,
    "seed": 20503,
    "device": "cuda"
  },
  "final": {
    "soft_mse_full": 0.9236739873886108,
    "discrete_mse": 133.48594665527344,
    "hash_match": false,
    "perm_str": "39,75,59,52,42,78,95,63,56,30,44,82,94,55,68,29,18,80,88,93,69,72,86,90,37,19,10,7,35,24,15,67,73,47,48,57,1,26,87,71,3,25,31,36,50,66,23,38,64,40,5,51,4,32,14,17,81,11,16,20,65,6,77,92,45,33,28,70,61,53,41,34,62,83,43,76,0,9,60,54,2,21,91,12,13,79,74,96,84,22,58,89,27,46,49,8,85",
    "in_cols": [
      18,
      29,
      20,
      47,
      27,
      22,
      46,
      35,
      11,
      44,
      36,
      42,
      17,
      6,
      16,
      9,
      37,
      24,
      1,
      43,
      3,
      15,
      26,
      12,
      33,
      5,
      4,
      8,
      40,
      10,
      34,
      39,
      23,
      14,
      31,
      19,
      32,
      21,
      0,
      30,
      2,
      45,
      7,
      38,
      41,
      28,
      13,
      25
    ],
    "out_cols": [
      36,
      25,
      38,
      30,
      15,
      41,
      28,
      14,
      40,
      46,
      35,
      44,
      7,
      1,
      11,
      32,
      23,
      29,
      13,
      34,
      12,
      19,
      31,
      20,
      21,
      24,
      16,
      6,
      4,
      8,
      0,
      45,
      17,
      33,
      26,
      18,
      42,
      37,
      3,
      27,
      9,
      5,
      39,
      47,
      10,
      43,
      22,
      2
    ]
  },
  "best_seen": {
    "discrete_mse": 32.36886978149414,
    "order": [
      [
        27,
        8
      ],
      [
        18,
        57
      ],
      [
        64,
        33
      ],
      [
        74,
        6
      ],
      [
        41,
        83
      ],
      [
        43,
        30
      ],
      [
        31,
        26
      ],
      [
        45,
        9
      ],
      [
        35,
        24
      ],
      [
        44,
        55
      ],
      [
        91,
        19
      ],
      [
        59,
        63
      ],
      [
        16,
        67
      ],
      [
        69,
        51
      ],
      [
        86,
        34
      ],
      [
        14,
        92
      ],
      [
        58,
        53
      ],
      [
        1,
        75
      ],
      [
        88,
        40
      ],
      [
        50,
        38
      ],
      [
        65,
        12
      ],
      [
        28,
        54
      ],
      [
        39,
        20
      ],
      [
        77,
        72
      ],
      [
        56,
        90
      ],
      [
        60,
        22
      ],
      [
        37,
        7
      ],
      [
        68,
        70
      ],
      [
        95,
        66
      ],
      [
        61,
        76
      ],
      [
        87,
        25
      ],
      [
        15,
        71
      ],
      [
        0,
        96
      ],
      [
        62,
        11
      ],
      [
        94,
        82
      ],
      [
        4,
        79
      ],
      [
        13,
        36
      ],
      [
        3,
        93
      ],
      [
        73,
        78
      ],
      [
        42,
        80
      ],
      [
        84,
        89
      ],
      [
        23,
        46
      ],
      [
        48,
        17
      ],
      [
        81,
        29
      ],
      [
        49,
        32
      ],
      [
        5,
        47
      ],
      [
        2,
        21
      ],
      [
        10,
        52
      ]
    ],
    "in_cols": [
      13,
      11,
      33,
      38,
      19,
      21,
      15,
      23,
      16,
      22,
      45,
      29,
      10,
      36,
      42,
      8,
      28,
      1,
      44,
      26,
      34,
      14,
      18,
      39,
      27,
      30,
      17,
      35,
      47,
      31,
      43,
      9,
      0,
      32,
      46,
      4,
      7,
      3,
      37,
      20,
      41,
      12,
      24,
      40,
      25,
      5,
      2,
      6
    ],
    "out_cols": [
      2,
      29,
      17,
      0,
      42,
      15,
      13,
      3,
      11,
      28,
      7,
      30,
      32,
      24,
      18,
      45,
      26,
      36,
      21,
      20,
      5,
      27,
      8,
      35,
      44,
      10,
      1,
      33,
      31,
      37,
      12,
      34,
      47,
      4,
      41,
      39,
      19,
      46,
      38,
      40,
      43,
      22,
      6,
      14,
      16,
      23,
      9,
      25
    ]
  }
}