{
  "config": {
    "steps": 900,
    "lr": 0.03,
    "tau_start": 1.0,
    "tau_end": 0.03,
    "sinkhorn_iters": 30,
    "lambda_ent": 0.0003,
    "train_subsample": 4096,
    "seed": 13701,
    "device": "cuda"
  },
  "final": {
    "soft_mse_full": 0.3589649200439453,
    "discrete_mse": 3.5958304405212402,
    "hash_match": false,
    "perm_str": "95,52,59,25,50,63,58,78,56,30,74,55,88,54,42,29,44,82,69,67,84,72,94,93,86,7,48,47,18,90,15,80,68,26,73,36,39,19,37,57,3,66,35,24,1,40,23,38,87,71,27,51,5,17,14,11,45,92,77,20,91,33,4,32,81,96,62,6,16,53,41,75,2,70,60,21,10,8,49,34,0,12,65,79,28,9,43,76,61,46,64,22,31,83,13,89,85",
    "in_cols": [
      47,
      29,
      26,
      28,
      27,
      38,
      44,
      20,
      22,
      36,
      41,
      46,
      42,
      24,
      11,
      9,
      35,
      37,
      18,
      17,
      3,
      16,
      1,
      12,
      43,
      13,
      5,
      8,
      23,
      39,
      45,
      4,
      40,
      32,
      10,
      19,
      2,
      30,
      6,
      25,
      0,
      34,
      14,
      21,
      31,
      33,
      15,
      7
    ],
    "out_cols": [
      25,
      12,
      30,
      38,
      15,
      28,
      27,
      14,
      41,
      32,
      35,
      46,
      1,
      23,
      44,
      40,
      13,
      19,
      7,
      29,
      31,
      11,
      21,
      20,
      34,
      24,
      6,
      4,
      45,
      8,
      17,
      16,
      47,
      0,
      26,
      36,
      33,
      9,
      2,
      18,
      5,
      39,
      3,
      37,
      22,
      10,
      42,
      43
    ]
  },
  "best_seen": {
    "discrete_mse": 1.5932376384735107,
    "order": [
      [
        95,
        52
      ],
      [
        59,
        25
      ],
      [
        50,
        63
      ],
      [
        77,
        78
      ],
      [
        56,
        30
      ],
      [
        74,
        55
      ],
      [
        88,
        54
      ],
      [
        42,
        29
      ],
      [
        44,
        82
      ],
      [
        69,
        67
      ],
      [
        94,
        72
      ],
      [
        58,
        93
      ],
      [
        86,
        7
      ],
      [
        48,
        47
      ],
      [
        18,
        90
      ],
      [
        15,
        80
      ],
      [
        68,
        26
      ],
      [
        73,
        36
      ],
      [
        39,
        19
      ],
      [
        37,
        57
      ],
      [
        3,
        66
      ],
      [
        35,
        24
      ],
      [
        1,
        40
      ],
      [
        23,
        38
      ],
      [
        87,
        71
      ],
      [
        27,
        51
      ],
      [
        28,
        17
      ],
      [
        14,
        11
      ],
      [
        45,
        92
      ],
      [
        5,
        20
      ],
      [
        91,
        33
      ],
      [
        4,
        32
      ],
      [
        81,
        96
      ],
      [
        62,
        6
      ],
      [
        16,
        53
      ],
      [
        41,
        75
      ],
      [
        2,
        70
      ],
      [
        60,
        21
      ],
      [
        10,
        8
      ],
      [
        49,
        34
      ],
      [
        0,
        12
      ],
      [
        65,
        79
      ],
      [
        84,
        9
      ],
      [
        43,
        76
      ],
      [
        61,
        46
      ],
      [
        64,
        22
      ],
      [
        31,
        83
      ],
      [
        13,
        89
      ]
    ],
    "in_cols": [
      47,
      29,
      26,
      39,
      27,
      38,
      44,
      20,
      22,
      36,
      46,
      28,
      42,
      24,
      11,
      9,
      35,
      37,
      18,
      17,
      3,
      16,
      1,
      12,
      43,
      13,
      14,
      8,
      23,
      5,
      45,
      4,
      40,
      32,
      10,
      19,
      2,
      30,
      6,
      25,
      0,
      34,
      41,
      21,
      31,
      33,
      15,
      7
    ],
    "out_cols": [
      25,
      12,
      30,
      38,
      15,
      28,
      27,
      14,
      41,
      32,
      35,
      46,
      1,
      23,
      44,
      40,
      13,
      19,
      7,
      29,
      31,
      11,
      21,
      20,
      34,
      24,
      6,
      4,
      45,
      8,
      17,
      16,
      47,
      0,
      26,
      36,
      33,
      9,
      2,
      18,
      5,
      39,
      3,
      37,
      22,
      10,
      42,
      43
    ]
  }
}