{
  "config": {
    "steps": 700,
    "lr": 0.015,
    "tau_start": 1.0,
    "tau_end": 0.025,
    "sinkhorn_iters": 30,
    "lambda_ent": 0.0001,
    "train_subsample": 0,
    "seed": 22004,
    "device": "cuda"
  },
  "final": {
    "soft_mse_full": 0.3428531289100647,
    "discrete_mse": 133.9938507080078,
    "hash_match": false,
    "perm_str": "59,52,18,30,39,72,95,63,56,82,44,78,68,80,42,29,73,55,58,93,69,67,94,90,48,47,10,19,35,24,15,57,1,7,37,40,87,66,28,71,3,26,31,36,50,25,0,38,14,17,64,51,5,32,81,75,13,11,77,33,4,6,16,20,62,96,74,70,91,53,65,89,61,54,60,21,27,46,2,83,86,34,45,79,23,22,88,9,84,92,41,76,49,8,43,12,85",
    "in_cols": [
      29,
      11,
      18,
      47,
      27,
      22,
      35,
      20,
      37,
      28,
      36,
      46,
      24,
      6,
      16,
      9,
      1,
      17,
      43,
      14,
      3,
      15,
      26,
      0,
      8,
      33,
      5,
      40,
      7,
      39,
      4,
      10,
      32,
      38,
      45,
      34,
      31,
      30,
      13,
      2,
      42,
      23,
      12,
      44,
      41,
      19,
      25,
      21
    ],
    "out_cols": [
      25,
      15,
      35,
      30,
      41,
      38,
      40,
      14,
      28,
      46,
      32,
      44,
      23,
      7,
      11,
      29,
      1,
      21,
      31,
      34,
      13,
      19,
      12,
      20,
      6,
      24,
      16,
      36,
      4,
      17,
      0,
      8,
      47,
      33,
      26,
      43,
      27,
      9,
      22,
      42,
      18,
      39,
      10,
      3,
      45,
      37,
      2,
      5
    ]
  },
  "best_seen": {
    "discrete_mse": 6.503526210784912,
    "order": [
      [
        64,
        83
      ],
      [
        50,
        20
      ],
      [
        39,
        46
      ],
      [
        65,
        54
      ],
      [
        43,
        21
      ],
      [
        35,
        17
      ],
      [
        45,
        52
      ],
      [
        2,
        63
      ],
      [
        14,
        29
      ],
      [
        86,
        79
      ],
      [
        84,
        72
      ],
      [
        69,
        66
      ],
      [
        68,
        25
      ],
      [
        28,
        96
      ],
      [
        49,
        12
      ],
      [
        59,
        53
      ],
      [
        73,
        6
      ],
      [
        31,
        70
      ],
      [
        88,
        80
      ],
      [
        0,
        8
      ],
      [
        58,
        11
      ],
      [
        61,
        55
      ],
      [
        95,
        7
      ],
      [
        77,
        32
      ],
      [
        81,
        92
      ],
      [
        13,
        78
      ],
      [
        5,
        51
      ],
      [
        42,
        76
      ],
      [
        16,
        89
      ],
      [
        23,
        47
      ],
      [
        41,
        33
      ],
      [
        37,
        36
      ],
      [
        18,
        30
      ],
      [
        94,
        22
      ],
      [
        3,
        24
      ],
      [
        15,
        82
      ],
      [
        91,
        9
      ],
      [
        44,
        19
      ],
      [
        10,
        34
      ],
      [
        48,
        90
      ],
      [
        56,
        38
      ],
      [
        1,
        71
      ],
      [
        74,
        67
      ],
      [
        87,
        26
      ],
      [
        4,
        40
      ],
      [
        62,
        75
      ],
      [
        60,
        93
      ],
      [
        27,
        57
      ]
    ],
    "in_cols": [
      33,
      26,
      18,
      34,
      21,
      16,
      23,
      2,
      8,
      42,
      41,
      36,
      35,
      14,
      25,
      29,
      37,
      15,
      44,
      0,
      28,
      31,
      47,
      39,
      40,
      7,
      5,
      20,
      10,
      12,
      19,
      17,
      11,
      46,
      3,
      9,
      45,
      22,
      6,
      24,
      27,
      1,
      38,
      43,
      4,
      32,
      30,
      13
    ],
    "out_cols": [
      42,
      8,
      22,
      27,
      9,
      6,
      25,
      30,
      14,
      39,
      35,
      31,
      12,
      47,
      5,
      26,
      0,
      33,
      40,
      2,
      4,
      28,
      1,
      16,
      45,
      38,
      24,
      37,
      43,
      23,
      17,
      19,
      15,
      10,
      11,
      41,
      3,
      7,
      18,
      44,
      20,
      34,
      32,
      13,
      21,
      36,
      46,
      29
    ]
  }
}