{
  "config": {
    "steps": 900,
    "lr": 0.03,
    "tau_start": 1.0,
    "tau_end": 0.03,
    "sinkhorn_iters": 30,
    "lambda_ent": 0.0003,
    "train_subsample": 4096,
    "seed": 20501,
    "device": "cuda"
  },
  "final": {
    "soft_mse_full": 0.4260350465774536,
    "discrete_mse": 5.339229583740234,
    "hash_match": false,
    "perm_str": "59,52,39,55,49,72,95,78,56,30,74,80,44,82,42,29,3,54,69,67,86,71,94,93,18,90,73,7,48,47,37,57,28,19,35,24,27,40,1,63,87,25,50,66,31,26,14,75,23,38,5,11,4,51,15,6,65,32,62,20,91,92,16,33,43,70,81,96,77,83,61,53,0,36,41,76,45,22,84,46,10,17,68,8,13,9,58,34,60,89,2,21,64,79,88,12,85",
    "in_cols": [
      29,
      18,
      25,
      47,
      27,
      38,
      22,
      20,
      3,
      36,
      42,
      46,
      11,
      37,
      24,
      17,
      14,
      16,
      13,
      1,
      43,
      26,
      15,
      8,
      12,
      5,
      4,
      9,
      34,
      32,
      45,
      10,
      21,
      40,
      39,
      31,
      0,
      19,
      23,
      41,
      6,
      35,
      7,
      28,
      30,
      2,
      33,
      44
    ],
    "out_cols": [
      25,
      28,
      35,
      38,
      15,
      40,
      41,
      14,
      27,
      32,
      34,
      46,
      44,
      1,
      23,
      29,
      7,
      11,
      21,
      30,
      12,
      31,
      13,
      36,
      20,
      4,
      24,
      0,
      16,
      8,
      45,
      17,
      33,
      47,
      42,
      26,
      19,
      37,
      10,
      22,
      6,
      2,
      3,
      18,
      43,
      9,
      39,
      5
    ]
  },
  "best_seen": {
    "discrete_mse": 1.0982210636138916,
    "order": [
      [
        59,
        52
      ],
      [
        39,
        55
      ],
      [
        95,
        72
      ],
      [
        3,
        78
      ],
      [
        56,
        30
      ],
      [
        74,
        80
      ],
      [
        44,
        82
      ],
      [
        68,
        29
      ],
      [
        42,
        54
      ],
      [
        69,
        67
      ],
      [
        86,
        71
      ],
      [
        94,
        93
      ],
      [
        18,
        36
      ],
      [
        73,
        7
      ],
      [
        48,
        47
      ],
      [
        37,
        57
      ],
      [
        28,
        19
      ],
      [
        35,
        24
      ],
      [
        27,
        40
      ],
      [
        1,
        63
      ],
      [
        87,
        25
      ],
      [
        50,
        66
      ],
      [
        31,
        26
      ],
      [
        14,
        75
      ],
      [
        23,
        38
      ],
      [
        5,
        11
      ],
      [
        4,
        51
      ],
      [
        15,
        6
      ],
      [
        65,
        32
      ],
      [
        62,
        20
      ],
      [
        91,
        92
      ],
      [
        16,
        33
      ],
      [
        43,
        70
      ],
      [
        81,
        96
      ],
      [
        77,
        83
      ],
      [
        61,
        53
      ],
      [
        0,
        90
      ],
      [
        41,
        76
      ],
      [
        45,
        22
      ],
      [
        84,
        46
      ],
      [
        10,
        17
      ],
      [
        49,
        8
      ],
      [
        13,
        9
      ],
      [
        58,
        34
      ],
      [
        60,
        89
      ],
      [
        2,
        21
      ],
      [
        64,
        79
      ],
      [
        88,
        12
      ]
    ],
    "in_cols": [
      29,
      18,
      47,
      3,
      27,
      38,
      22,
      35,
      20,
      36,
      42,
      46,
      11,
      37,
      24,
      17,
      14,
      16,
      13,
      1,
      43,
      26,
      15,
      8,
      12,
      5,
      4,
      9,
      34,
      32,
      45,
      10,
      21,
      40,
      39,
      31,
      0,
      19,
      23,
      41,
      6,
      25,
      7,
      28,
      30,
      2,
      33,
      44
    ],
    "out_cols": [
      25,
      28,
      35,
      38,
      15,
      40,
      41,
      14,
      27,
      32,
      34,
      46,
      19,
      1,
      23,
      29,
      7,
      11,
      21,
      30,
      12,
      31,
      13,
      36,
      20,
      4,
      24,
      0,
      16,
      8,
      45,
      17,
      33,
      47,
      42,
      26,
      44,
      37,
      10,
      22,
      6,
      2,
      3,
      18,
      43,
      9,
      39,
      5
    ]
  }
}