{
  "config": {
    "steps": 900,
    "lr": 0.03,
    "tau_start": 1.0,
    "tau_end": 0.028,
    "sinkhorn_iters": 30,
    "lambda_ent": 0.0003,
    "train_subsample": 4096,
    "seed": 28702,
    "device": "cuda"
  },
  "final": {
    "soft_mse_full": 0.3603474497795105,
    "discrete_mse": 2.741521120071411,
    "hash_match": false,
    "perm_str": "59,52,39,30,95,80,16,63,44,82,68,72,42,29,5,93,69,78,94,53,18,67,35,40,86,90,48,19,37,7,50,36,15,57,73,47,1,24,28,71,3,26,31,25,87,38,91,92,14,11,64,33,77,17,4,32,81,6,45,55,62,96,65,20,43,70,74,54,13,66,41,79,23,75,84,34,0,83,60,46,58,21,27,89,56,9,49,8,2,51,61,12,88,22,10,76,85",
    "in_cols": [
      29,
      18,
      47,
      10,
      22,
      35,
      20,
      5,
      36,
      46,
      11,
      16,
      42,
      24,
      17,
      26,
      9,
      37,
      1,
      14,
      3,
      15,
      43,
      45,
      8,
      33,
      39,
      4,
      40,
      23,
      32,
      34,
      21,
      38,
      7,
      19,
      12,
      41,
      0,
      30,
      28,
      13,
      27,
      25,
      2,
      31,
      44,
      6
    ],
    "out_cols": [
      25,
      15,
      40,
      30,
      41,
      35,
      14,
      46,
      38,
      26,
      32,
      21,
      44,
      7,
      1,
      19,
      29,
      23,
      11,
      34,
      13,
      12,
      20,
      45,
      4,
      17,
      6,
      16,
      0,
      28,
      47,
      8,
      33,
      27,
      31,
      39,
      36,
      18,
      42,
      22,
      9,
      43,
      3,
      2,
      24,
      5,
      10,
      37
    ]
  },
  "best_seen": {
    "discrete_mse": 1.1232331991195679,
    "order": [
      [
        59,
        52
      ],
      [
        39,
        30
      ],
      [
        62,
        80
      ],
      [
        95,
        63
      ],
      [
        44,
        82
      ],
      [
        68,
        72
      ],
      [
        42,
        29
      ],
      [
        81,
        93
      ],
      [
        69,
        78
      ],
      [
        94,
        53
      ],
      [
        18,
        67
      ],
      [
        35,
        40
      ],
      [
        86,
        90
      ],
      [
        48,
        19
      ],
      [
        37,
        7
      ],
      [
        50,
        36
      ],
      [
        15,
        57
      ],
      [
        73,
        47
      ],
      [
        1,
        24
      ],
      [
        28,
        71
      ],
      [
        3,
        26
      ],
      [
        31,
        25
      ],
      [
        87,
        38
      ],
      [
        91,
        92
      ],
      [
        14,
        11
      ],
      [
        64,
        33
      ],
      [
        77,
        17
      ],
      [
        4,
        32
      ],
      [
        5,
        6
      ],
      [
        45,
        79
      ],
      [
        16,
        96
      ],
      [
        65,
        20
      ],
      [
        43,
        70
      ],
      [
        74,
        54
      ],
      [
        13,
        66
      ],
      [
        41,
        55
      ],
      [
        23,
        75
      ],
      [
        84,
        34
      ],
      [
        0,
        83
      ],
      [
        60,
        46
      ],
      [
        58,
        21
      ],
      [
        27,
        89
      ],
      [
        56,
        9
      ],
      [
        49,
        8
      ],
      [
        2,
        51
      ],
      [
        61,
        12
      ],
      [
        88,
        22
      ],
      [
        10,
        76
      ]
    ],
    "in_cols": [
      29,
      18,
      32,
      47,
      22,
      35,
      20,
      40,
      36,
      46,
      11,
      16,
      42,
      24,
      17,
      26,
      9,
      37,
      1,
      14,
      3,
      15,
      43,
      45,
      8,
      33,
      39,
      4,
      5,
      23,
      10,
      34,
      21,
      38,
      7,
      19,
      12,
      41,
      0,
      30,
      28,
      13,
      27,
      25,
      2,
      31,
      44,
      6
    ],
    "out_cols": [
      25,
      15,
      40,
      30,
      41,
      35,
      14,
      46,
      38,
      26,
      32,
      21,
      44,
      7,
      1,
      19,
      29,
      23,
      11,
      34,
      13,
      12,
      20,
      45,
      4,
      17,
      6,
      16,
      0,
      39,
      47,
      8,
      33,
      27,
      31,
      28,
      36,
      18,
      42,
      22,
      9,
      43,
      3,
      2,
      24,
      5,
      10,
      37
    ]
  }
}